{
  "swagger": "2.0",
  "info": {
    "title": "order/v1/api/order-api.proto",
    "version": "version not set"
  },
  "tags": [
    {
      "name": "OrderService"
    }
  ],
  "consumes": [
    "application/json"
  ],
  "produces": [
    "application/json"
  ],
  "paths": {
    "/api/v1/order": {
      "get": {
        "operationId": "OrderService_List",
        "responses": {
          "200": {
            "description": "",
            "schema": {
              "type": "array",
              "items": {
                "type": "object",
                "$ref": "#/definitions/v1Order"
              }
            }
          },
          "default": {
            "description": "An unexpected error response.",
            "schema": {
              "$ref": "#/definitions/googlerpcStatus"
            }
          }
        },
        "tags": [
          "OrderService"
        ]
      },
      "post": {
        "operationId": "OrderService_Create",
        "responses": {
          "200": {
            "description": "A successful response.",
            "schema": {
              "$ref": "#/definitions/v1OrderCreateResponse"
            }
          },
          "default": {
            "description": "An unexpected error response.",
            "schema": {
              "$ref": "#/definitions/googlerpcStatus"
            }
          }
        },
        "parameters": [
          {
            "name": "body",
            "in": "body",
            "required": true,
            "schema": {
              "$ref": "#/definitions/v1OrderCreateRequest"
            }
          }
        ],
        "tags": [
          "OrderService"
        ]
      }
    },
    "/api/v1/order/approve": {
      "post": {
        "operationId": "OrderService_Approve",
        "responses": {
          "200": {
            "description": "A successful response.",
            "schema": {
              "$ref": "#/definitions/v1OrderApproveResponse"
            }
          },
          "default": {
            "description": "An unexpected error response.",
            "schema": {
              "$ref": "#/definitions/googlerpcStatus"
            }
          }
        },
        "parameters": [
          {
            "name": "body",
            "in": "body",
            "required": true,
            "schema": {
              "$ref": "#/definitions/v1OrderApproveRequest"
            }
          }
        ],
        "tags": [
          "OrderService"
        ]
      }
    },
    "/api/v1/order/cancel": {
      "post": {
        "operationId": "OrderService_Cancel",
        "responses": {
          "200": {
            "description": "A successful response.",
            "schema": {
              "$ref": "#/definitions/v1OrderCancelResponse"
            }
          },
          "default": {
            "description": "An unexpected error response.",
            "schema": {
              "$ref": "#/definitions/googlerpcStatus"
            }
          }
        },
        "parameters": [
          {
            "name": "body",
            "in": "body",
            "required": true,
            "schema": {
              "$ref": "#/definitions/v1OrderCancelRequest"
            }
          }
        ],
        "tags": [
          "OrderService"
        ]
      }
    },
    "/api/v1/order/release": {
      "post": {
        "operationId": "OrderService_Release",
        "responses": {
          "200": {
            "description": "A successful response.",
            "schema": {
              "$ref": "#/definitions/v1OrderReleaseResponse"
            }
          },
          "default": {
            "description": "An unexpected error response.",
            "schema": {
              "$ref": "#/definitions/googlerpcStatus"
            }
          }
        },
        "parameters": [
          {
            "name": "body",
            "in": "body",
            "required": true,
            "schema": {
              "$ref": "#/definitions/v1OrderReleaseRequest"
            }
          }
        ],
        "tags": [
          "OrderService"
        ]
      }
    },
    "/api/v1/order/resume": {
      "post": {
        "operationId": "OrderService_Resume",
        "responses": {
          "200": {
            "description": "A successful response.",
            "schema": {
              "$ref": "#/definitions/v1OrderResumeResponse"
            }
          },
          "default": {
            "description": "An unexpected error response.",
            "schema": {
              "$ref": "#/definitions/googlerpcStatus"
            }
          }
        },
        "parameters": [
          {
            "name": "body",
            "in": "body",
            "required": true,
            "schema": {
              "$ref": "#/definitions/v1OrderResumeRequest"
            }
          }
        ],
        "tags": [
          "OrderService"
        ]
      }
    },
    "/api/v1/order/{id}": {
      "get": {
        "operationId": "OrderService_Get",
        "responses": {
          "200": {
            "description": "",
            "schema": {
              "$ref": "#/definitions/v1Order"
            }
          },
          "default": {
            "description": "An unexpected error response.",
            "schema": {
              "$ref": "#/definitions/googlerpcStatus"
            }
          }
        },
        "parameters": [
          {
            "name": "id",
            "in": "path",
            "required": true,
            "type": "string"
          }
        ],
        "tags": [
          "OrderService"
        ]
      }
    }
  },
  "definitions": {
    "OrderCreateRequestOrderCreate": {
      "type": "object",
      "properties": {
        "items": {
          "type": "array",
          "items": {
            "type": "object",
            "$ref": "#/definitions/OrderCreateRequestOrderCreateItem"
          }
        },
        "customerId": {
          "type": "string"
        },
        "delivery": {
          "$ref": "#/definitions/OrderDelivery"
        }
      }
    },
    "OrderCreateRequestOrderCreateItem": {
      "type": "object",
      "properties": {
        "id": {
          "type": "string"
        },
        "amount": {
          "type": "integer",
          "format": "int32"
        }
      }
    },
    "OrderDelivery": {
      "type": "object",
      "properties": {
        "dateTime": {
          "type": "string",
          "format": "date-time",
          "x-nullable": true
        },
        "address": {
          "type": "string"
        },
        "type": {
          "$ref": "#/definitions/OrderDeliveryType"
        }
      }
    },
    "OrderDeliveryType": {
      "type": "string",
      "enum": [
        "PICKUP",
        "COURIER"
      ],
      "default": "PICKUP"
    },
    "googlerpcStatus": {
      "type": "object",
      "properties": {
        "code": {
          "type": "integer",
          "format": "int32"
        },
        "message": {
          "type": "string"
        },
        "details": {
          "type": "array",
          "items": {
            "type": "object",
            "$ref": "#/definitions/protobufAny"
          }
        }
      }
    },
    "protobufAny": {
      "type": "object",
      "properties": {
        "@type": {
          "type": "string"
        }
      },
      "additionalProperties": {}
    },
    "v1Order": {
      "type": "object",
      "properties": {
        "id": {
          "type": "string"
        },
        "createdAt": {
          "type": "string",
          "format": "date-time"
        },
        "updatedAt": {
          "type": "string",
          "format": "date-time"
        },
        "customerId": {
          "type": "string"
        },
        "paymentId": {
          "type": "string",
          "x-nullable": true
        },
        "reserveId": {
          "type": "string",
          "x-nullable": true
        },
        "status": {
          "$ref": "#/definitions/v1OrderStatus"
        },
        "paymentStatus": {
          "$ref": "#/definitions/v1PaymentStatus",
          "x-nullable": true
        },
        "delivery": {
          "$ref": "#/definitions/OrderDelivery",
          "x-nullable": true
        },
        "items": {
          "type": "array",
          "items": {
            "type": "object",
            "$ref": "#/definitions/v1ReserveItem"
          }
        }
      }
    },
    "v1OrderApproveRequest": {
      "type": "object",
      "properties": {
        "id": {
          "type": "string"
        },
        "twoPhaseCommit": {
          "type": "boolean"
        }
      }
    },
    "v1OrderApproveResponse": {
      "type": "object",
      "properties": {
        "id": {
          "type": "string"
        },
        "status": {
          "$ref": "#/definitions/v1OrderStatus",
          "x-nullable": true
        }
      }
    },
    "v1OrderCancelRequest": {
      "type": "object",
      "properties": {
        "id": {
          "type": "string"
        },
        "twoPhaseCommit": {
          "type": "boolean"
        }
      }
    },
    "v1OrderCancelResponse": {
      "type": "object",
      "properties": {
        "id": {
          "type": "string"
        },
        "status": {
          "$ref": "#/definitions/v1OrderStatus",
          "x-nullable": true
        }
      }
    },
    "v1OrderCreateRequest": {
      "type": "object",
      "properties": {
        "body": {
          "$ref": "#/definitions/OrderCreateRequestOrderCreate"
        },
        "twoPhaseCommit": {
          "type": "boolean"
        }
      }
    },
    "v1OrderCreateResponse": {
      "type": "object",
      "properties": {
        "id": {
          "type": "string"
        }
      }
    },
    "v1OrderGetResponse": {
      "type": "object",
      "properties": {
        "order": {
          "$ref": "#/definitions/v1Order"
        }
      }
    },
    "v1OrderListResponse": {
      "type": "object",
      "properties": {
        "orders": {
          "type": "array",
          "items": {
            "type": "object",
            "$ref": "#/definitions/v1Order"
          }
        }
      }
    },
    "v1OrderReleaseRequest": {
      "type": "object",
      "properties": {
        "id": {
          "type": "string"
        },
        "twoPhaseCommit": {
          "type": "boolean"
        }
      }
    },
    "v1OrderReleaseResponse": {
      "type": "object",
      "properties": {
        "id": {
          "type": "string"
        },
        "status": {
          "$ref": "#/definitions/v1OrderStatus",
          "x-nullable": true
        }
      }
    },
    "v1OrderResumeRequest": {
      "type": "object",
      "properties": {
        "id": {
          "type": "string"
        },
        "twoPhaseCommit": {
          "type": "boolean"
        }
      }
    },
    "v1OrderResumeResponse": {
      "type": "object",
      "properties": {
        "id": {
          "type": "string"
        },
        "status": {
          "$ref": "#/definitions/v1OrderStatus"
        }
      }
    },
    "v1OrderStatus": {
      "type": "string",
      "enum": [
        "CREATING",
        "CREATED",
        "APPROVING",
        "APPROVED",
        "RELEASING",
        "RELEASED",
        "INSUFFICIENT",
        "CANCELLING",
        "CANCELLED"
      ],
      "default": "CREATING"
    },
    "v1PaymentStatus": {
      "type": "string",
      "enum": [
        "CREATED",
        "HOLD",
        "INSUFFICIENT",
        "PAID",
        "CANCELLED"
      ],
      "default": "CREATED"
    },
    "v1ReserveItem": {
      "type": "object",
      "properties": {
        "id": {
          "type": "string"
        },
        "amount": {
          "type": "integer",
          "format": "int32"
        },
        "insufficient": {
          "type": "integer",
          "format": "int32",
          "x-nullable": true
        },
        "reserved": {
          "type": "boolean"
        }
      }
    }
  }
}
